porto_task/__init__.py
porto_task-0.1.0.dist-info/WHEEL
porto_task-0.1.0.dist-info/METADATA
porto_task-0.1.0.dist-info/RECORD
