Metadata-Version: 2.1
Name: porto-task
Version: 0.1.0
Summary: 
Author: Scirpus22
Author-email: yurikamysh@gmail.com
Requires-Python: >=3.7.1,<4.0.0
Classifier: Programming Language :: Python :: 3
Classifier: Programming Language :: Python :: 3.8
Classifier: Programming Language :: Python :: 3.9
Requires-Dist: matplotlib (>=3.3.4,<4.0.0)
Requires-Dist: numpy (==1.19.5)
Requires-Dist: pandas (>=1.2.2,<2.0.0)
Requires-Dist: scikit-learn (>=0.24.1,<0.25.0)
Requires-Dist: tensorflow (>=2.4.1,<3.0.0)
